README.md
setup.py
fortunate/__init__.py
fortunate/fortunes
fortunate.egg-info/PKG-INFO
fortunate.egg-info/SOURCES.txt
fortunate.egg-info/dependency_links.txt
fortunate.egg-info/entry_points.txt
fortunate.egg-info/pbr.json
fortunate.egg-info/top_level.txt