Metadata-Version: 2.1
Name: fortunate
Version: 1.4.0
Summary: Python version of old BSD Unix fortune program
Home-page: https://github.com/Kronuz/fortunate
Author: German Mendez Bravo (Kronuz), Brian M. Clapper
Author-email: german.mb@gmail.com, bmc@clapper.org
License: BSD-style license
Platform: UNKNOWN
Classifier: Intended Audience :: End Users/Desktop
Classifier: Operating System :: OS Independent
Classifier: Topic :: Games/Entertainment
Classifier: License :: OSI Approved :: BSD License
Classifier: Programming Language :: Python
Classifier: Topic :: Text Processing :: Filters
